calcfu/__init__.py
calcfu/calc_config.py
calcfu/calculator.py
calcfu/exceptions.py
calcfu/plate.py
calcfu/utils.py
calcfu-1.0.1.dist-info/LICENSE
calcfu-1.0.1.dist-info/METADATA
calcfu-1.0.1.dist-info/WHEEL
calcfu-1.0.1.dist-info/top_level.txt
calcfu-1.0.1.dist-info/RECORD
