Metadata-Version: 2.1
Name: calcfu
Version: 1.0.1
Summary: This package contains the CalCFU and Plate class for automatically calculating CFU counts under the NCIMS 2400 standards.
Home-page: https://github.com/koisland/CalCFU/tree/py_mod
Author: Keith Oshima
Author-email: koshima789@gmail.com
License: MIT
Classifier: License :: OSI Approved :: MIT License
License-File: LICENSE
